msfabric-0.1.0.data/data/requirements.txt
pyfabric/__init__.py
pyfabric/auth.py
pyfabric/base.py
pyfabric/capacity.py
pyfabric/capacity_.py
pyfabric/dax.py
pyfabric/lakehouse.py
pyfabric/semantic_model.py
pyfabric/workspace.py
pyfabric/config/__init__.py
pyfabric/services/__init__.py
pyfabric/services/graph.py
scripts/__init__.py
scripts/get_project_version.py
msfabric-0.1.0.dist-info/LICENSE
msfabric-0.1.0.dist-info/METADATA
msfabric-0.1.0.dist-info/WHEEL
msfabric-0.1.0.dist-info/top_level.txt
msfabric-0.1.0.dist-info/RECORD
