Metadata-Version: 2.1
Name: msfabric
Version: 0.1.0
Summary: English: MS Fabric library for interacting with the Fabric ecosystem API. Español: Biblioteca de Microsoft Fabric para interactuar con la API del ecosistema de Fabric.
Home-page: https://dalatic.com
Author: Dalatic S.L | Jonathan Cuéllar Viveros
Author-email: jcuellar@dalatic.com
License: Proprietary
Requires-Python: >=3.10
License-File: LICENSE
Requires-Dist: azure-core
Requires-Dist: azure-identity
Requires-Dist: azure-storage-blob
Requires-Dist: azure-storage-file-datalake
Requires-Dist: boto3
Requires-Dist: botocore
Requires-Dist: certifi
Requires-Dist: cffi
Requires-Dist: charset-normalizer
Requires-Dist: cryptography
Requires-Dist: idna
Requires-Dist: install
Requires-Dist: isodate
Requires-Dist: jmespath
Requires-Dist: msal
Requires-Dist: msal-extensions
Requires-Dist: packaging
Requires-Dist: portalocker
Requires-Dist: pycparser
Requires-Dist: PyJWT
Requires-Dist: python-dateutil
Requires-Dist: requests
Requires-Dist: s3transfer
Requires-Dist: setuptools
Requires-Dist: six
Requires-Dist: typing-extensions
Requires-Dist: urllib3
Requires-Dist: pandas
Requires-Dist: pyarrow
Requires-Dist: azure-mgmt-resource
Requires-Dist: azure-mgmt-resourcegraph
